gql_alchemy/__init__.py
gql_alchemy/errors.py
gql_alchemy/executor.py
gql_alchemy/parser.py
gql_alchemy/query_model.py
gql_alchemy/raw_reader.py
gql_alchemy/resolvers.py
gql_alchemy/schema.py
gql_alchemy/types.py
gql_alchemy/utils.py
gql_alchemy/validator.py
gql_alchemy-0.0.1.dist-info/DESCRIPTION.rst
gql_alchemy-0.0.1.dist-info/METADATA
gql_alchemy-0.0.1.dist-info/RECORD
gql_alchemy-0.0.1.dist-info/WHEEL
gql_alchemy-0.0.1.dist-info/metadata.json
gql_alchemy-0.0.1.dist-info/top_level.txt
