Metadata-Version: 2.0
Name: gql-alchemy
Version: 0.0.1
Summary: GraphQL implementation
Home-page: https://github.com/gql-alchemy/gql-alchemy
Author: Dmitry Maslennikov
Author-email: maslennikovdm+gql-alchemy@gmail.com
License: MIT
Keywords: graphql
Platform: UNKNOWN
Classifier: Development Status :: 3 - Alpha
Classifier: Programming Language :: Python :: 3.6
Requires-Python: ~=3.6
